{
  "headers": {
    "cross-origin-opener-policy": "same-origin",
    "strict-transport-security": "max-age=63072000; includeSubDomains; preload",
    "cross-origin-resource-policy": "same-origin",
    "x-amz-version-id": "66l3By5m76lOhInJDiT3pyEwsLWpUHft",
    "content-security-policy": "default-src 'none'; style-src 'unsafe-inline'; sandbox",
    "server": "deno/gcp-europe-north1",
    "x-content-type-options": "nosniff",
    "x-amz-cf-pop": "HEL51-P2",
    "cross-origin-embedder-policy": "same-origin",
    "vary": "Accept-Encoding, Origin",
    "server-timing": "fetchSource;dur=982",
    "x-amz-cf-id": "OSQXeCF7r4VLxIme4KKRVB6P0--uLY5sVMdcbuaPeQnSFxBOC3B2mg==",
    "via": "http/2 edgeproxy-h",
    "access-control-allow-origin": "*",
    "x-frame-options": "DENY",
    "etag": "W/\"25707dc564e3caa86eff65a1e3c8043a\"",
    "age": "9056515",
    "x-amz-replication-status": "COMPLETED",
    "x-cache": "Hit from cloudfront",
    "content-type": "application/javascript",
    "referrer-policy": "strict-origin-when-cross-origin",
    "cache-control": "public, max-age=31536000, immutable",
    "last-modified": "Fri, 25 Mar 2022 13:32:49 GMT",
    "date": "Fri, 26 May 2023 13:26:28 GMT"
  },
  "url": "https://deno.land/std@0.132.0/node/_process/streams.mjs",
  "now": {
    "secs_since_epoch": 1694164104,
    "nanos_since_epoch": 259805923
  }
}